ChaRan/__init__.py
charan_teja_pkg-0.1.dist-info/METADATA
charan_teja_pkg-0.1.dist-info/WHEEL
charan_teja_pkg-0.1.dist-info/top_level.txt
charan_teja_pkg-0.1.dist-info/RECORD
