Metadata-Version: 2.4
Name: charan_teja_pkg
Version: 0.1
Summary: This speech to plain text package
Author: Rachaveti Charan Teja
Author-email: charante153624@gmail.com
Dynamic: author
Dynamic: author-email
Dynamic: summary
